guhs_server/__init__.py
guhs_server/boot_script.py
guhs_server/server.py
guhs_server/shell.py
guhs_server/storage.py
guhs_server-2.dist-info/LICENSE
guhs_server-2.dist-info/METADATA
guhs_server-2.dist-info/WHEEL
guhs_server-2.dist-info/entry_points.txt
guhs_server-2.dist-info/top_level.txt
guhs_server-2.dist-info/RECORD
