Metadata-Version: 2.1
Name: guhs-server
Version: 2
Summary: GRUB UEFI HTTP Selector Server
Home-page: https://github.com/jamofer/guhs-server
Author: Javier Moragón
Author-email: jamofer@gmail.com
License: UNKNOWN
Platform: UNKNOWN
Classifier: Development Status :: 4 - Beta
Classifier: Intended Audience :: Developers
Classifier: License :: OSI Approved :: MIT License
Classifier: Operating System :: POSIX :: Linux
Classifier: Programming Language :: Python :: 3.7
Classifier: Topic :: System :: Boot
Classifier: Topic :: System :: Boot :: Init
Classifier: Topic :: Internet
Classifier: Topic :: Internet :: WWW/HTTP
Requires-Python: >=3.7
License-File: LICENSE
Requires-Dist: flask
Provides-Extra: testing
Requires-Dist: flake8 ; extra == 'testing'
Requires-Dist: pytest ; extra == 'testing'
Requires-Dist: mock ; extra == 'testing'
